adaptive/__init__.py
adaptive/adaptive_engine.py
adaptive/adaptive_enhancements.py
adaptive/adaptive_memory.py
adaptive/microbiome_network.py
bioshield_integration-3.2.2.dist-info/licenses/AUTHORS.md
modules/__init__.py
modules/web_api_fetcher.py
modules/agro_immunity/__init__.py
modules/agro_immunity/agro_immunity_wrapper.py
modules/agro_immunity/basic_module.py
modules/aquacrop/__init__.py
modules/aquacrop/aquacrop_wrapper.py
modules/aquacrop/basic_module.py
modules/hydronet/__init__.py
modules/hydronet/basic_module.py
modules/hydronet/hydronet_wrapper.py
modules/pathogen_intel/__init__.py
modules/pathogen_intel/data/__init__.py
modules/smart_executor/__init__.py
modules/smart_executor/basic_module.py
modules/smart_executor/smart_executor_wrapper.py
orchestrator/__init__.py
orchestrator/cascade_manager.py
orchestrator/data_router.py
bioshield_integration-3.2.2.dist-info/METADATA
bioshield_integration-3.2.2.dist-info/WHEEL
bioshield_integration-3.2.2.dist-info/top_level.txt
bioshield_integration-3.2.2.dist-info/RECORD
