Metadata-Version: 2.4
Name: bioshield-integration
Version: 3.2.2
Summary: BioShield Integration: Unified Intelligence Framework with Enhanced Pathogen Risk Assessment
Home-page: https://github.com/emerladcompass/BioShield-Integration
Author: Emerlad Compass
Author-email: Emerlad Compass <emerladcompass@gmail.com>
License: MIT
Project-URL: Homepage, https://github.com/emerladcompass/BioShield-Integration
Project-URL: Repository, https://github.com/emerladcompass/BioShield-Integration
Project-URL: Issues, https://github.com/emerladcompass/BioShield-Integration/issues
Classifier: Development Status :: 5 - Production/Stable
Classifier: License :: OSI Approved :: MIT License
Classifier: Programming Language :: Python :: 3.8
Classifier: Programming Language :: Python :: 3.9
Classifier: Programming Language :: Python :: 3.10
Classifier: Programming Language :: Python :: 3.11
Classifier: Programming Language :: Python :: 3.12
Classifier: Topic :: Scientific/Engineering :: Artificial Intelligence
Classifier: Topic :: Scientific/Engineering :: Bio-Informatics
Requires-Python: >=3.8
License-File: AUTHORS.md
Requires-Dist: numpy>=1.21.0
Requires-Dist: scipy>=1.7.0
Requires-Dist: pyyaml>=6.0
Dynamic: author
Dynamic: home-page
Dynamic: license-file
Dynamic: requires-python
